azure/mgmt/baremetalinfrastructure/__init__.py
azure/mgmt/baremetalinfrastructure/_bare_metal_infrastructure_client.py
azure/mgmt/baremetalinfrastructure/_configuration.py
azure/mgmt/baremetalinfrastructure/_version.py
azure/mgmt/baremetalinfrastructure/aio/__init__.py
azure/mgmt/baremetalinfrastructure/aio/_bare_metal_infrastructure_client.py
azure/mgmt/baremetalinfrastructure/aio/_configuration.py
azure/mgmt/baremetalinfrastructure/aio/operations/__init__.py
azure/mgmt/baremetalinfrastructure/aio/operations/_azure_bare_metal_instances_operations.py
azure/mgmt/baremetalinfrastructure/aio/operations/_operations.py
azure/mgmt/baremetalinfrastructure/models/__init__.py
azure/mgmt/baremetalinfrastructure/models/_bare_metal_infrastructure_client_enums.py
azure/mgmt/baremetalinfrastructure/models/_models.py
azure/mgmt/baremetalinfrastructure/models/_models_py3.py
azure/mgmt/baremetalinfrastructure/operations/__init__.py
azure/mgmt/baremetalinfrastructure/operations/_azure_bare_metal_instances_operations.py
azure/mgmt/baremetalinfrastructure/operations/_operations.py
azure_mgmt_baremetalinfrastructure-1.0.0.dist-info/METADATA
azure_mgmt_baremetalinfrastructure-1.0.0.dist-info/WHEEL
azure_mgmt_baremetalinfrastructure-1.0.0.dist-info/top_level.txt
azure_mgmt_baremetalinfrastructure-1.0.0.dist-info/RECORD
